{
   "type": "FeatureCollection",
   "features": [
  {
    "type": "Feature",
    "geometry": {
       "type": "Point",
       "coordinates":  [ 126.9745,37.6282 ]
    },
    "properties": {
    "Address_dong":"평창동",
    "Name":"보현봉",
    "Category":"mtn_main"
    }
  },
  {
    "type": "Feature",
    "geometry": {
       "type": "Point",
       "coordinates":  [ 126.9827,37.6197 ]
    },
    "properties": {
    "Address_dong":"평창동",
    "Name":"형제봉",
    "Category":"mtn_sub"
    }
  },
  {
    "type": "Feature",
    "geometry": {
       "type": "Point",
       "coordinates":  [ 126.9572,37.6263 ]
    },
    "properties": {
    "Address_dong":"평창동",
    "Name":"비봉",
    "Category":"mtn_sub"
    }
  },
  {
    "type": "Feature",
    "geometry": {
       "type": "Point",
       "coordinates":  [ 126.9618,37.6012 ]
    },
    "properties": {
    "Address_dong":"평창동",
    "Name":"수구",
    "Category":"river"
    }
  }
]
}